rocketbotte/__init__.py
rocketbotte/bot.py
rocketbotte/exceptions.py
rocketbotte/models.py
rocketbotte-0.2.4.dist-info/WHEEL
rocketbotte-0.2.4.dist-info/METADATA
rocketbotte-0.2.4.dist-info/RECORD
