Metadata-Version: 2.3
Name: rocketbotte
Version: 0.2.4
Summary: A bot for rocketchat messaging, allowing you to react to messages or commands.
Keywords: rocketchat,rocket chat,bot
Author: Styfore
Author-email: Styfore <rocketbotte@styfore.ovh>
Requires-Dist: aiohttp[speedups]>=3.11.18,<4.0.0
Requires-Dist: loguru>=0.7.3,<0.8.0
Requires-Python: >=3.11, <4.0
Project-URL: Bug Tracker, https://codeberg.org/styfore/rocketbotte/issues
Project-URL: repository, https://codeberg.org/styfore/rocketbotte.git
